[
  {
    "name": "Glock 17",
    "manufacturer": "Glock",
    "caliber": "9×19mm Parabellum",
    "category": "Handgun",
    "image": "https://upload.wikimedia.org/wikipedia/commons/thumb/f/f7/Glock_17_Gen_4_Pistol.jpg/220px-Glock_17_Gen_4_Pistol.jpg"
  },
  {
    "name": "AK-47",
    "manufacturer": "Kalashnikov Concern",
    "caliber": "7.62×39mm",
    "category": "Rifle",
    "image": "https://upload.wikimedia.org/wikipedia/commons/thumb/f/f0/AK-47_type_II_Part_DM-ST-89-01131.jpg/220px-AK-47_type_II_Part_DM-ST-89-01131.jpg"
  },
  {
    "name": "M4 Carbine",
    "manufacturer": "Colt",
    "caliber": "5.56×45mm NATO",
    "category": "Rifle",
    "image": "https://upload.wikimedia.org/wikipedia/commons/thumb/9/9f/M4_Carbine_CQBR.jpg/220px-M4_Carbine_CQBR.jpg"
  }
]
